{ "compressionlevel":-1,
 "height":35,
 "infinite":false,
 "layers":[
        {
         "id":3,
         "image":"full scene.png",
         "imageheight":1136,
         "imagewidth":1072,
         "name":"background",
         "opacity":1,
         "type":"imagelayer",
         "visible":true,
         "x":0,
         "y":0
        }, 
        {
         "id":6,
         "image":"",
         "name":"bg",
         "opacity":1,
         "type":"imagelayer",
         "visible":true,
         "x":0,
         "y":0
        }, 
        {
         "draworder":"topdown",
         "id":1,
         "name":"Collisions",
         "objects":[
                {
                 "height":46,
                 "id":1,
                 "name":"wall_bottom",
                 "opacity":1,
                 "rotation":0,
                 "type":"",
                 "visible":true,
                 "width":1072,
                 "x":19.8068366793271,
                 "y":1135.0388341989
                }, 
                {
                 "height":160,
                 "id":2,
                 "name":"wall_top",
                 "opacity":1,
                 "rotation":0,
                 "type":"",
                 "visible":true,
                 "width":1072,
                 "x":13.0600728625689,
                 "y":2.87156034415899
                }, 
                {
                 "height":1136,
                 "id":3,
                 "name":"wall_left",
                 "opacity":1,
                 "rotation":0,
                 "type":"",
                 "visible":true,
                 "width":80,
                 "x":8,
                 "y":126
                }, 
                {
                 "height":1136,
                 "id":4,
                 "name":"wall_right",
                 "opacity":1,
                 "rotation":0,
                 "type":"",
                 "visible":true,
                 "width":80,
                 "x":1060.72087435083,
                 "y":2.87156034415899
                }, 
                {
                 "height":75.9999999999999,
                 "id":24,
                 "name":"",
                 "opacity":1,
                 "rotation":0,
                 "type":"",
                 "visible":true,
                 "width":5.99999999999999,
                 "x":71.133090458104,
                 "y":1029.39219181976
                }, 
                {
                 "height":60.6666666666666,
                 "id":25,
                 "name":"",
                 "opacity":1,
                 "rotation":0,
                 "type":"",
                 "visible":true,
                 "width":280,
                 "x":39.133090458104,
                 "y":760.725525153089
                }, 
                {
                 "height":210,
                 "id":26,
                 "name":"",
                 "opacity":1,
                 "rotation":0,
                 "type":"",
                 "visible":true,
                 "width":91.3333333333333,
                 "x":65.7997571247707,
                 "y":781.392191819756
                }, 
                {
                 "height":90.6666666666666,
                 "id":27,
                 "name":"",
                 "opacity":1,
                 "rotation":0,
                 "type":"",
                 "visible":true,
                 "width":70.6666666666667,
                 "x":104.466423791437,
                 "y":936.725525153089
                }, 
                {
                 "height":64.5,
                 "id":28,
                 "name":"trashcan",
                 "opacity":1,
                 "rotation":0,
                 "type":"",
                 "visible":true,
                 "width":105.333333333333,
                 "x":173.799757124771,
                 "y":983.058858486422
                }, 
                {
                 "height":62.6666666666666,
                 "id":55,
                 "name":"",
                 "opacity":1,
                 "rotation":0,
                 "type":"",
                 "visible":true,
                 "width":200,
                 "x":329.799757124771,
                 "y":762.725525153089
                }, 
                {
                 "height":89.3333333333334,
                 "id":56,
                 "name":"",
                 "opacity":1,
                 "rotation":0,
                 "type":"",
                 "visible":true,
                 "width":218.666666666667,
                 "x":264.466423791437,
                 "y":764.058858486422
                }, 
                {
                 "height":103.333333333333,
                 "id":58,
                 "name":"",
                 "opacity":1,
                 "rotation":0,
                 "type":"",
                 "visible":true,
                 "width":470,
                 "x":223.799757124771,
                 "y":685.392191819756
                }, 
                {
                 "height":34.0000000000001,
                 "id":59,
                 "name":"",
                 "opacity":1,
                 "rotation":0,
                 "type":"",
                 "visible":true,
                 "width":8,
                 "x":781.799757124771,
                 "y":603.392191819755
                }, 
                {
                 "height":46.6666666666667,
                 "id":60,
                 "name":"",
                 "opacity":1,
                 "rotation":0,
                 "type":"",
                 "visible":true,
                 "width":22.6666666666667,
                 "x":760.466423791437,
                 "y":625.392191819755
                }, 
                {
                 "height":21.3333333333333,
                 "id":61,
                 "name":"",
                 "opacity":1,
                 "rotation":0,
                 "type":"",
                 "visible":true,
                 "width":34.6666666666666,
                 "x":739.133090458104,
                 "y":658.725525153089
                }, 
                {
                 "height":14.6666666666666,
                 "id":62,
                 "name":"",
                 "opacity":1,
                 "rotation":0,
                 "type":"",
                 "visible":true,
                 "width":65.3333333333333,
                 "x":703.133090458104,
                 "y":685.392191819756
                }, 
                {
                 "height":16,
                 "id":63,
                 "name":"",
                 "opacity":1,
                 "rotation":0,
                 "type":"",
                 "visible":true,
                 "width":68,
                 "x":707.133090458104,
                 "y":676.058858486422
                }, 
                {
                 "height":102.666666666667,
                 "id":64,
                 "name":"",
                 "opacity":1,
                 "rotation":0,
                 "type":"",
                 "visible":true,
                 "width":26.6666666666666,
                 "x":665.799757124771,
                 "y":689.392191819756
                }, 
                {
                 "height":36,
                 "id":65,
                 "name":"",
                 "opacity":1,
                 "rotation":0,
                 "type":"",
                 "visible":true,
                 "width":54.6666666666667,
                 "x":680.466423791437,
                 "y":680.058858486422
                }, 
                {
                 "height":78.6666666666666,
                 "id":70,
                 "name":"",
                 "opacity":1,
                 "rotation":0,
                 "type":"",
                 "visible":true,
                 "width":88,
                 "x":989.799757124771,
                 "y":434.725525153089
                }, 
                {
                 "height":80,
                 "id":71,
                 "name":"",
                 "opacity":1,
                 "rotation":0,
                 "type":"",
                 "visible":true,
                 "width":154.666666666667,
                 "x":925.799757124771,
                 "y":360.058858486422
                }, 
                {
                 "height":101.333333333333,
                 "id":72,
                 "name":"",
                 "opacity":1,
                 "rotation":0,
                 "type":"",
                 "visible":true,
                 "width":118.666666666667,
                 "x":812.466423791437,
                 "y":321.392191819756
                }, 
                {
                 "height":58.6666666666666,
                 "id":73,
                 "name":"",
                 "opacity":1,
                 "rotation":0,
                 "type":"",
                 "visible":true,
                 "width":236,
                 "x":668.466423791437,
                 "y":293.392191819756
                }, 
                {
                 "height":32,
                 "id":74,
                 "name":"",
                 "opacity":1,
                 "rotation":0,
                 "type":"",
                 "visible":true,
                 "width":157.333333333333,
                 "x":723.133090458104,
                 "y":357.392191819756
                }, 
                {
                 "height":18.6666666666667,
                 "id":75,
                 "name":"",
                 "opacity":1,
                 "rotation":0,
                 "type":"",
                 "visible":true,
                 "width":81.3333333333333,
                 "x":771.133090458104,
                 "y":393.392191819756
                }, 
                {
                 "height":46.6666666666667,
                 "id":76,
                 "name":"",
                 "opacity":1,
                 "rotation":0,
                 "type":"",
                 "visible":true,
                 "width":121.333333333333,
                 "x":560.466423791437,
                 "y":268.058858486422
                }, 
                {
                 "height":92,
                 "id":77,
                 "name":"",
                 "opacity":1,
                 "rotation":0,
                 "type":"",
                 "visible":true,
                 "width":84,
                 "x":475.133090458104,
                 "y":253.392191819756
                }, 
                {
                 "height":408,
                 "id":78,
                 "name":"",
                 "opacity":1,
                 "rotation":0,
                 "type":"",
                 "visible":true,
                 "width":88,
                 "x":181.799757124771,
                 "y":366.725525153089
                }, 
                {
                 "height":180,
                 "id":79,
                 "name":"",
                 "opacity":1,
                 "rotation":0,
                 "type":"",
                 "visible":true,
                 "width":61.3333333333333,
                 "x":267.133090458104,
                 "y":601.392191819755
                }, 
                {
                 "height":142.666666666667,
                 "id":81,
                 "name":"",
                 "opacity":1,
                 "rotation":0,
                 "type":"",
                 "visible":true,
                 "width":97.3333333333333,
                 "x":371.133090458104,
                 "y":269.392191819756
                }, 
                {
                 "height":140,
                 "id":82,
                 "name":"",
                 "opacity":1,
                 "rotation":0,
                 "type":"",
                 "visible":true,
                 "width":85.3333333333333,
                 "x":412.466423791437,
                 "y":252.058858486422
                }, 
                {
                 "height":57.3333333333334,
                 "id":83,
                 "name":"",
                 "opacity":1,
                 "rotation":0,
                 "type":"",
                 "visible":true,
                 "width":141.333333333333,
                 "x":251.133090458104,
                 "y":361.392191819756
                }, 
                {
                 "height":49.3333333333333,
                 "id":84,
                 "name":"",
                 "opacity":1,
                 "rotation":0,
                 "type":"",
                 "visible":true,
                 "width":77.3333333333333,
                 "x":288.466423791437,
                 "y":418.725525153089
                },
            
                {
                 "height":181.5,
                 "id":90,
                 "name":"",
                 "opacity":1,
                 "rotation":0,
                 "type":"",
                 "visible":true,
                 "width":141,
                 "x":556,
                 "y":770
                }],
         "opacity":1,
         "type":"objectgroup",
         "visible":true,
         "x":0,
         "y":0
        }, 
        {
         "draworder":"topdown",
         "id":5,
         "name":"Interactables",
         "objects":[
                {
                 "height":160.666666666667,
                 "id":85,
                 "name":"inspect_answering_machine",
                 "opacity":1,
                 "rotation":0,
                 "type":"",
                 "visible":true,
                 "width":207,
                 "x":246.666666666667,
                 "y":346.666666666667
                }, 
                {
                 "height":152.666666666667,
                 "id":86,
                 "name":"inspect_takeout_bag",
                 "opacity":1,
                 "rotation":0,
                 "type":"",
                 "visible":true,
                 "width":106.666666666667,
                 "x":799,
                 "y":326.666666666667
                }, 
                {
                 "height":172.666666666667,
                 "id":87,
                 "name":"inspect_calendar",
                 "opacity":1,
                 "rotation":0,
                 "type":"",
                 "visible":true,
                 "width":120,
                 "x":940.666666666667,
                 "y":769.333333333333
                }, 
                {
                 "height":95.3333333333334,
                 "id":88,
                 "name":"inspect_newspaper",
                 "opacity":1,
                 "rotation":0,
                 "type":"",
                 "visible":true,
                 "width":94.6666666666666,
                 "x":662.666666666667,
                 "y":505.333333333333
                }, 
                {
                 "height":136.666666666667,
                 "id":89,
                 "name":"inspect_trash_can",
                 "opacity":1,
                 "rotation":0,
                 "type":"",
                 "visible":true,
                 "width":121.333333333333,
                 "x":175.833333333333,
                 "y":887.166666666667
                }],
         "opacity":1,
         "type":"objectgroup",
         "visible":true,
         "x":0,
         "y":0
        }, 
        {
         "draworder":"topdown",
         "id":2,
         "name":"Triggers",
         "objects":[
                {
                 "height":403.634912022324,
                 "id":10,
                 "name":"desk_fade",
                 "opacity":1,
                 "rotation":0,
                 "type":"",
                 "visible":true,
                 "width":466.417073611865,
                 "x":253.505464692659,
                 "y":335.271839392295
                }, 
                {
                 "height":624.432447097128,
                 "id":11,
                 "name":"cabinet_fade",
                 "opacity":1,
                 "rotation":0,
                 "type":"",
                 "visible":true,
                 "width":307.64785675529,
                 "x":854.92132392871,
                 "y":514.24959305504
                }],
         "opacity":1,
         "type":"objectgroup",
         "visible":false,
         "x":0,
         "y":0
        }],
 "nextlayerid":7,
 "nextobjectid":91,
 "orientation":"orthogonal",
 "renderorder":"right-down",
 "tiledversion":"1.12.1",
 "tileheight":32,
 "tilesets":[],
 "tilewidth":32,
 "type":"map",
 "version":"1.10",
 "width":33
}